model_uploader/__init__.py
model_uploader/uploader.py
model_uploader-0.1.dist-info/LICENSE
model_uploader-0.1.dist-info/METADATA
model_uploader-0.1.dist-info/WHEEL
model_uploader-0.1.dist-info/top_level.txt
model_uploader-0.1.dist-info/RECORD
